simmpst/__init__.py
simmpst/tokenization.py
simmpst-0.1.1.dist-info/METADATA
simmpst-0.1.1.dist-info/WHEEL
simmpst-0.1.1.dist-info/top_level.txt
simmpst-0.1.1.dist-info/RECORD
