Metadata-Version: 2.1
Name: simmpst
Version: 0.1.1
Summary: Simbolo Multilingual Partial-syllable Tokenizer
Home-page: https://github.com/SaPhyoThuHtet/multilingual-partial-syllable-tokenizer
Download-URL: https://github.com/SaPhyoThuHtet/multilingual-partial-syllable-tokenizer/archive/0.1.0.tar.gz
Author: Sa Phyo Thu Htet
Author-email: phyothuhtet@simbolomm.com
License: MIT
Classifier: Programming Language :: Python :: 3
Classifier: License :: OSI Approved :: MIT License
Classifier: Operating System :: OS Independent
Requires-Python: >=3.6
Requires-Dist: tensorflow >=2.15.0
Requires-Dist: keras >=2.15.0
